gila/__init__.py
gila/gila.py
gila/util/__init__.py
gila/util/errors.py
gila/util/helpers.py
gila-0.5.0.dist-info/LICENSE
gila-0.5.0.dist-info/METADATA
gila-0.5.0.dist-info/WHEEL
gila-0.5.0.dist-info/top_level.txt
gila-0.5.0.dist-info/RECORD
