Metadata-Version: 2.1
Name: gila
Version: 0.5.0
Summary: A simple python3 config library based ongolang's spf13/viper
Home-page: https://gitlab.com/dashwav/gila
Author: dashwav
License: MPL2.0
Platform: UNKNOWN
Classifier: Development Status :: 4 - Beta
Classifier: License :: OSI Approved :: Mozilla Public License 2.0 (MPL 2.0)
Classifier: Programming Language :: Python :: 3.6
Classifier: Programming Language :: Python :: 3.7
Classifier: Programming Language :: Python :: 3.8
Classifier: Programming Language :: Python :: 3 :: Only
Classifier: Intended Audience :: Developers
Classifier: Natural Language :: English
Requires-Dist: PyYAML (==5.1.2)
Requires-Dist: toml (==0.10.0)
Requires-Dist: pyhcl (==0.3.13)
Requires-Dist: python-dotenv (==0.10.3)
